my_python_api/__init__.py
my_python_api/_python_api.cpython-37m-x86_64-linux-gnu.so
example_python_extension_cpp-0.0.3.dist-info/top_level.txt
example_python_extension_cpp-0.0.3.dist-info/WHEEL
example_python_extension_cpp-0.0.3.dist-info/METADATA
example_python_extension_cpp-0.0.3.dist-info/RECORD
