Metadata-Version: 2.1
Name: example-python-extension-cpp
Version: 0.0.3
Summary: A minimal C++ extension using pybind11 and vcpkg
Author-email: Andreu Gimenez <esdandreu@gmail.com>
License: BSD 3-Clause License
Project-URL: homepage, https://github.com/esdandreu/python-extension-cpp
Project-URL: repository, https://github.com/esdandreu/python-extension-cpp
Keywords: example,vcpkg,pybind11,scikit-build,cpp
Requires-Python: >=3.7
Provides-Extra: test
Requires-Dist: pytest ; extra == 'test'
